uv_publish.py
uv_publish-1.3.dist-info/METADATA
uv_publish-1.3.dist-info/WHEEL
uv_publish-1.3.dist-info/entry_points.txt
uv_publish-1.3.dist-info/top_level.txt
uv_publish-1.3.dist-info/RECORD
