Metadata-Version: 2.4
Name: uv-publish
Version: 1.3
Summary: Wrapper tool ito run `uv publish` using default credentials from `~/.pypirc`
Author-email: Mark Blakeney <mark.blakeney@bullet-systems.net>
License-Expression: GPL-3.0-or-later
Project-URL: Homepage, https://github.com/bulletmark/uv-publish
Keywords: uv,pypi,twine,hatch,flit,pdm
Classifier: Programming Language :: Python :: 3
Requires-Python: >=3.8
